cardsboard/__init__.py
cardsboard/__main__.py
cardsboard/cardsboard.py
cardsboard/config.py
cardsboard/fsdb.py
cardsboard-0.1.2.dist-info/LICENSE
cardsboard-0.1.2.dist-info/METADATA
cardsboard-0.1.2.dist-info/WHEEL
cardsboard-0.1.2.dist-info/entry_points.txt
cardsboard-0.1.2.dist-info/top_level.txt
cardsboard-0.1.2.dist-info/RECORD
