Metadata-Version: 2.1
Name: cardsboard
Version: 0.1.2
Summary: Terminal Kanban board
Author-email: Markus Kreft <mail@mkreft.de>
License: The MIT License (MIT)
Project-URL: Homepage, https://github.com/markus-kreft/cardsboard
Project-URL: Bug Tracker, https://github.com/markus-kreft/cardsboard/issues
Keywords: kanban,tui,todo,cards,board,project management
Classifier: Programming Language :: Python :: 3
Classifier: Development Status :: 4 - Beta
Classifier: Operating System :: POSIX :: Linux
Classifier: License :: OSI Approved :: MIT License
Classifier: Environment :: Console :: Curses
Classifier: Intended Audience :: End Users/Desktop
Classifier: Topic :: Utilities
Requires-Python: >=3.6
License-File: LICENSE
